LICENSE.txt
MANIFEST.in
README.md
pyproject.toml
setup.cfg
setup.py
src/wmm2015/CMakeLists.txt
src/wmm2015/WMM.COF
src/wmm2015/__init__.py
src/wmm2015/base.py
src/wmm2015/build.py
src/wmm2015/meson.build
src/wmm2015/plots.py
src/wmm2015/setup.cmake
src/wmm2015/test_input.asc
src/wmm2015.egg-info/PKG-INFO
src/wmm2015.egg-info/SOURCES.txt
src/wmm2015.egg-info/dependency_links.txt
src/wmm2015.egg-info/not-zip-safe
src/wmm2015.egg-info/requires.txt
src/wmm2015.egg-info/top_level.txt
src/wmm2015/src/EGM9615.h
src/wmm2015/src/GeomagnetismHeader.h
src/wmm2015/src/GeomagnetismLibrary.c
src/wmm2015/src/wmm_file.c
src/wmm2015/src/wmm_grid.c
src/wmm2015/src/wmm_point.c
src/wmm2015/src/wmm_point_sub.c